setup.py
typology/__init__.py
typology/utils.py
typology.egg-info/PKG-INFO
typology.egg-info/SOURCES.txt
typology.egg-info/dependency_links.txt
typology.egg-info/not-zip-safe
typology.egg-info/requires.txt
typology.egg-info/top_level.txt
typology/ontology/__init__.py
typology/ontology/infinity.py
typology/ontology/test_infinity.py
typology/ontology/test_wikidata.py
typology/ontology/wikidata.py