Metadata-Version: 2.1
Name: typology
Version: 0.1.4
Summary: Python formats derived from vocabulary concepts.
Home-page: https://github.com/wefindx/typology
Author: Mindey
Author-email: mindey@qq.com
License: AGPL
Platform: UNKNOWN
Provides-Extra: test
